charty/__init__.py
charty/frontend/build/asset-manifest.json
charty/frontend/build/bootstrap.min.css
charty/frontend/build/index.html
charty/frontend/build/precache-manifest.ca3d0590e910e3b6ccfb1e0626f847a3.js
charty/frontend/build/service-worker.js
charty/frontend/build/static/js/2.27bd71cc.chunk.js
charty/frontend/build/static/js/2.27bd71cc.chunk.js.LICENSE.txt
charty/frontend/build/static/js/2.27bd71cc.chunk.js.map
charty/frontend/build/static/js/main.804ec37d.chunk.js
charty/frontend/build/static/js/main.804ec37d.chunk.js.map
charty/frontend/build/static/js/runtime-main.b42ca973.js
charty/frontend/build/static/js/runtime-main.b42ca973.js.map
streamlit_charty-0.0.2.dist-info/LICENSE
streamlit_charty-0.0.2.dist-info/METADATA
streamlit_charty-0.0.2.dist-info/WHEEL
streamlit_charty-0.0.2.dist-info/top_level.txt
streamlit_charty-0.0.2.dist-info/RECORD
