Metadata-Version: 2.1
Name: streamlit-charty
Version: 0.0.2
Summary: UNKNOWN
Home-page: 
Author: Anthony Alteirac
Author-email: 
License: UNKNOWN
Platform: UNKNOWN
Requires-Python: >=3.6
License-File: LICENSE
Requires-Dist: streamlit (>=0.63)
